README.rst
i18n.sh
setup.cfg
setup.py
docs/HISTORY.rst
docs/LICENSE.GPL
docs/LICENSE.txt
wm/__init__.py
wm.help.egg-info/PKG-INFO
wm.help.egg-info/SOURCES.txt
wm.help.egg-info/dependency_links.txt
wm.help.egg-info/entry_points.txt
wm.help.egg-info/namespace_packages.txt
wm.help.egg-info/not-zip-safe
wm.help.egg-info/requires.txt
wm.help.egg-info/top_level.txt
wm/help/__init__.py
wm/help/configure.zcml
wm/help/docs.pt
wm/help/docs.py
wm/help/interfaces.py
wm/help/example/__init__.py
wm/help/example/additional-documentation.rst
wm/help/example/configure.zcml
wm/help/example/plugin.py
wm/help/example/start.rst
wm/help/example/img/logo.png
wm/help/locales/manual.pot
wm/help/locales/wm.help.pot
wm/help/locales/de/LC_MESSAGES/wm.help.po
wm/help/profiles/default/actions.xml