Metadata-Version: 1.1
Name: wm.help
Version: 0.1
Summary: Infrastructure to add a ReStructuredText based help system to plone sites
Home-page: https://github.com/webmeisterei/wm.help
Author: Harald Friessnegger
Author-email: harald (at) webmeisterei dot com
License: GPL
Keywords: plone collective help documentation docutils rest restructuredtext rst
Platform: UNKNOWN
Classifier: Framework :: Plone
Classifier: Programming Language :: Python
Classifier: Framework :: Plone
Classifier: Framework :: Plone :: 4.1
Classifier: Framework :: Plone :: 4.2
